{"QTurYq3P682/0SKVP++KZg==":"t_beholderflumph-1777x2503.jpeg","L5+VNAwmfj85XOMDrCKMEg==":"colors0-700x734.jpg","ZEijzoTv5p/usjxx790Y/g==":"image13.jpg","F53W6ImnoG0oDC0qFH72Zw==":"t_beholderflumph-2000x2817.jpg","l/9qCJGbScRlHuB9WcDmmA==":"t_deathkiss-1736x1220.jpg","bIhUzJyJX1B/PJucjjHiRA==":"t_deathkiss2-1736x2552.png","loR0BnRr1rdVVAInkqAzww==":"t_necroface-1727x2451.jpg","NXd7kLehCsYcjQxVXInBuQ==":"t_ramoth-1718x2278.jpg","bmJSwfmxsKxZYzjaYJrkvA==":"t_yochlol-2000x2251.png","Y9SuQXQZFAbV+/oqPh5Qsg==":"t_zombiebeholder-928x1376.png","hZwXi+GjpNAWX4wYgMKXuw==":"d_pokemon-1726x1157.png","0j2q+jDIA+SxxaZOtlXaaw==":"d_theredcave-2000x1143.png","MFtEyyw25Qnk9SJCQbU7IQ==":"change01-1645x747.png","NqJHjRDPIQY4zNv8FyVbsw==":"change03-1645x566.png","cABvmEgdwhPSy8g9ngtG6A==":"change02-1645x593.png","imJq7H880tDubmy++FbjrQ==":"colors0-2000x2096.jpg","rFxiKqTEzU2zDw6o797PYg==":"colors1-2000x1400.jpg","sSerYiedCzmldQ8urPi1pA==":"colors2-2000x1425.jpg","7pcf2nN+XzHHJE2CWt6biA==":"daniel-1-2000x1930.jpg","tCS5ZtDmBgmY6raneQj7Iw==":"red-blue1-2000x2396.jpg","SwKs3U+RIYhmnpD8E0TRvQ==":"red-blue2-2000x2544.jpg","JhH1WTDx5Nil0+4r4bRqsA==":"daniel-3-981x1402.png","/JEmx24Yv1qs1SM+za79WQ==":"meli-1-1353x1546.png","fP392l0OCGztWQHNceLevg==":"meli-4-1490x1931.png","UMPn1jBqtwYSEEeKPDqkhw==":"sabina-1-798x1024.jpg","T5KOSEQEST43aYlgOtkHUw==":"sabina-3-704x1024.jpg","hJTX73at7s772Lw+5DAE5A==":"sabina-6-783x1024.jpg","ZFus3GzrZDdVEAlIJCjCwA==":"sabina-8-779x1024.jpg","OtoUkG0de2uxP590+y4WLQ==":"sabina-9-1024x848.jpg","RTNlFHrcfHve4vSKwNyfNA==":"storyboard-4-1207x804.png","vMCxxMUFojFca9kSrhs20Q==":"image21.jpg","r3lcP2U0tafbacZ/adbYBw==":"background1.jpg","7QSPgx0ej2S4ihWgWNCHXw==":"comingsoon-1197x798.png","Jlv3zXRNpeik93BCyo9LDQ==":"logos-1-789x452.png","ujenTbBEFmT37FY0DvL6bg==":"me-860x884.png"}